{
    "id": 0,
    "idAutomacao": 0,
    "idCidade": 0,
    "idPeriodoDe": 0,
    "idPeriodoAte": 0,
    "idUsuario": 0,
    "vlrTotalFaturasDe": 0.0,
    "vlrTotalFaturasAte": 0.0,
    "qtdTotalFaturasDe": 0,
    "qtdTotalFaturasAte": 0,
    "idServicoCorte": 0,
    "idsSituacaoLigacao": [0],
    "idsSituacaoCobranca": [0],
    "idsSituacaoImovel": [0],
    "idsCategorias": [0],
    "idsGrupo": [0],
    "idsTipoFaturamento": [0],
    "ativo": false,
    "desconsClientesEspeciais": false,
    "desconsiderarLigacaoAcordo": true,
    "desconsiderarFaturasDebitos": false,
    "desconsiderarAcoesJudiciais": false,
    "desconsiderarWhiteList": false,
    "qtdeMaxOsPorDia": 0,
    "numDiasGerados": 0,
    "descricaoGeral": "",
    "idFaseAtual": 0,
    "idFaseAnterior": 0,
    "habilitarFasesCorte": false,
    "faseAnterior": "",
    "faseAtual": ""
}