{
    "idArrecadador": 0,
    "idTipoRegistro": 0,
    "idInconsistencia": 0,
    "idArrecadacao": 0,
    "quantidade": 0,
    "quantidadeProcessado": 0,
    "arquivo": "",
    "arrecadador": "",
    "idArrecadadorStr": "",
    "inconsistencia": "",
    "dataImportacao": "",
    "identificacaoBancaria": "",
    "manual": false,
    "valor": 0,
    "valorProcessado": 0,
    "taxaArrecadacao": 0,
    "guias":[{
        "idGuia": 0,
        "idLigacao": 0,
        "idArrecadacao": 0,
        "dataPagamento": "",
        "valorPago": 0,
        "faturas":[{
            "idInconsistencia": 0,
            "idArrecadacao": 0,
            "idArrecadador": 0,
            "idCliente": 0,
            "idGrupo": 0,
            "nivelErro": 0,
            "idPeriodo": 0,
            "idFatura": 0,
            "idGuia": 0,
            "idLigacao": 0,
            "inconsistencia": "",
            "dataVencimento": "",
            "dataPagamento": "",
            "dataCredito": "",
            "dataImportacao": "",
            "periodo": "",
            "linha": "",
            "arquivoEnvio": "",
            "arquivoEstorno": "",
            "valor": 0,
            "valorGuia": 0,
            "taxaArrecadacao": 0,
            "valorPago": 0,
            "valorExtorno": 0,
            "faturasGuia":[{
                "idInconsistencia": 0,
                "idFatura": 0,
                "idGuia": 0,
                "idPeriodo": 0,
                "dataVencimento": "",
                "dataImportacao": "",
                "valor": 0,
                "taxaArrecadacao": 0,
                "pagamentoDuplicado": false
            }]
        }]
    }],
    "faturas":[{
        "idInconsistencia": 0,
        "idArrecadacao": 0,
        "idArrecadador": 0,
        "idCliente": 0,
        "idGrupo": 0,
        "nivelErro": 0,
        "idPeriodo": 0,
        "idFatura": 0,
        "idGuia": 0,
        "idLigacao": 0,
        "inconsistencia": "",
        "dataVencimento": "",
        "dataPagamento": "",
        "dataCredito": "",
        "dataImportacao": "",
        "periodo": "",
        "linha": "",
        "arquivoEnvio": "",
        "arquivoEstorno": "",
        "valor": 0,
        "valorGuia": 0,
        "taxaArrecadacao": 0,
        "valorPago": 0,
        "valorExtorno": 0,
        "faturasGuia":[{
            "idInconsistencia": 0,
            "idFatura": 0,
            "idGuia": 0,
            "idPeriodo": 0,
            "dataVencimento": "",
            "dataImportacao": "",
            "valor": 0,
            "taxaArrecadacao": 0,
            "pagamentoDuplicado": false
        }]
    }]
}